{
  "filename": "football.txt",
  "path": "/show/local/change/football.txt",
  "sizekB": 5879,
  "last_modified_date": "2025-07-09",
  "creation_date": "2024-11-15",
  "content_chunks": [
    "Football athlete championship tennis basketball football. Speed engine model car engine car.",
    "Athlete football athlete basketball championship football football. Speed race engine car race.",
    "Basketball football tennis football. Model race model race speed model."
  ],
  "file_type": "txt",
  "tags": [
    "sport",
    "cars"
  ]
}