{
  "filename": "dress.docx",
  "path": "/only/dress.docx",
  "sizekB": 9455,
  "last_modified_date": "2015-06-09",
  "creation_date": "2001-05-08",
  "content_chunks": [
    "Designer designer designer dress dress runway model. Model speed engine model speed speed race.",
    "Runway trend trend dress model model. Model car speed speed model car race.",
    "Model trend runway trend designer dress model. Car car speed engine car."
  ],
  "file_type": "docx",
  "tags": [
    "fashion",
    "cars"
  ]
}