{
  "filename": "car.txt",
  "path": "/wife/rise/interesting/car.txt",
  "sizekB": 1992,
  "last_modified_date": "2024-04-16",
  "creation_date": "2017-11-25",
  "content_chunks": [
    "Car engine race. Basketball tennis athlete football. Dress model runway model runway trend.",
    "Model race speed engine engine. Championship basketball football athlete athlete football championship. Runway dress designer dress dress runway dress."
  ],
  "file_type": "txt",
  "tags": [
    "cars",
    "sport",
    "fashion"
  ]
}